gurddy/__init__.py
gurddy/constraint.py
gurddy/model.py
gurddy/utils.py
gurddy/variable.py
gurddy/solver/csp_solver.py
gurddy/solver/lp_solver.py
gurddy/solver/minimax_solver.py
gurddy/solver/scipy_solver.py
gurddy-0.1.8.dist-info/LICENSE
gurddy-0.1.8.dist-info/METADATA
gurddy-0.1.8.dist-info/WHEEL
gurddy-0.1.8.dist-info/top_level.txt
gurddy-0.1.8.dist-info/RECORD
