Metadata-Version: 2.1
Name: gurddy
Version: 0.1.8
Summary: Gurddy Python package.
Author-email: novo <novo.email@gmail.com>
License: MIT
Project-URL: Homepage, https://github.com/novvoo/gurddy
Project-URL: Repository, https://github.com/novvoo/gurddy
Project-URL: Changelog, https://github.com/novvoo/gurddy/releases
Classifier: Development Status :: 4 - Beta
Classifier: Intended Audience :: Developers
Classifier: Operating System :: OS Independent
Classifier: Programming Language :: Python :: 3
Classifier: Programming Language :: Python :: 3.8
Classifier: Programming Language :: Python :: 3.9
Classifier: Programming Language :: Python :: 3.10
Classifier: Programming Language :: Python :: 3.11
Classifier: Programming Language :: Python :: 3.12
Requires-Python: >=3.8
License-File: LICENSE
Requires-Dist: scipy>=1.9.0
Provides-Extra: dev
Requires-Dist: pytest>=7.0; extra == "dev"
Provides-Extra: scipy
Requires-Dist: scipy>=1.9.0; extra == "scipy"
